README.md
setup.cfg
setup.py
PyCommentAPI/__init__.py
PyCommentAPI/apihelper.py
PyCommentAPI/asynchelper.py
PyCommentAPI.egg-info/PKG-INFO
PyCommentAPI.egg-info/SOURCES.txt
PyCommentAPI.egg-info/dependency_links.txt
PyCommentAPI.egg-info/not-zip-safe
PyCommentAPI.egg-info/top_level.txt