Metadata-Version: 1.0
Name: PyCommentAPI
Version: 2.0
Summary: A simple, but extensible Python implementation for the comments.bot API
Home-page: UNKNOWN
Author: Fenicu
Author-email: FenaFenol@gmail.com
License: UNKNOWN
Platform: UNKNOWN
